open_colorimeter_utils/__init__.py
open_colorimeter_utils/calibration_cli_app.py
open_colorimeter_utils/data_fitting.py
open_colorimeter_utils-0.1.0.post2.dist-info/entry_points.txt
open_colorimeter_utils-0.1.0.post2.dist-info/LICENSE.txt~
open_colorimeter_utils-0.1.0.post2.dist-info/LICENSE.txt
open_colorimeter_utils-0.1.0.post2.dist-info/WHEEL
open_colorimeter_utils-0.1.0.post2.dist-info/METADATA
open_colorimeter_utils-0.1.0.post2.dist-info/RECORD
