Metadata-Version: 2.1
Name: open-colorimeter-utils
Version: 0.1.0.post2
Summary: Utilities for iorodeo's open colorimeter
Home-page: https://github.com/iorodeo/open-colorimeter-utils
License: MIT
Author: Will Dickson
Author-email: will@iorodeo.com
Requires-Python: >=3.10,<4.0
Classifier: Intended Audience :: Science/Research
Classifier: License :: OSI Approved :: MIT License
Classifier: Programming Language :: Python :: 3
Classifier: Programming Language :: Python :: 3.10
Classifier: Programming Language :: Python :: 3.11
Classifier: Topic :: Scientific/Engineering :: Chemistry
Classifier: Topic :: Scientific/Engineering :: Physics
Requires-Dist: click (>=8.1.3,<9.0.0)
Requires-Dist: matplotlib (>=3.6.1,<4.0.0)
Requires-Dist: numpy (>=1.23.4,<2.0.0)
Requires-Dist: tomli (>=2.0.1,<3.0.0)
Project-URL: Repository, https://github.com/iorodeo/open-colorimeter-utils
